civic_line_cli/__dev__.py
civic_line_cli/__init__.py
civic_line_cli/globalStates.py
civic_line_cli/main.py
civic_line_cli/helper/__init__.py
civic_line_cli/helper/aiProcessor.py
civic_line_cli/helper/aiUtils.py
civic_line_cli/helper/emailService.py
civic_line_cli/helper/scraper.py
civic_line_cli/helper/storedValues.py
civic_line_cli/helper/tasksManager.py
civic_line_cli/helper/webRequester.py
civic_line_cli/helper/prompts/political_text_classifier.txt
civic_line_cli/helper/prompts/political_text_summarizer.txt
civic_line_cli-1.17.dist-info/METADATA
civic_line_cli-1.17.dist-info/WHEEL
civic_line_cli-1.17.dist-info/entry_points.txt
civic_line_cli-1.17.dist-info/top_level.txt
civic_line_cli-1.17.dist-info/RECORD
