Metadata-Version: 2.4
Name: civic_line_cli
Version: 1.17
Summary: Dead simple email sending for developers
Author: Hemit Vimal Patel
Author-email: hemit@nextvoters.com
Requires-Dist: openai
Requires-Dist: psycopg2-binary
Requires-Dist: requests
Requires-Dist: beautifulsoup4
Requires-Dist: python-docx
Dynamic: author
Dynamic: author-email
Dynamic: description
Dynamic: description-content-type
Dynamic: requires-dist
Dynamic: summary
